licence.txt
setup.cfg
setup.py
saveframes/__init__.py
saveframes/save_frames.py
saveframes.egg-info/PKG-INFO
saveframes.egg-info/SOURCES.txt
saveframes.egg-info/dependency_links.txt
saveframes.egg-info/not-zip-safe
saveframes.egg-info/top_level.txt