Metadata-Version: 2.1
Name: saveframes
Version: 0.1
Summary: This model is developed to save image frames from given video, arguments to be passed to function are video path & image count to start from
Author: Yuvraj Hembade
License-File: licence.txt
